{"login":"wolever","id":59575,"node_id":"MDQ6VXNlcjU5NTc1","avatar_url":"https://avatars.githubusercontent.com/u/59575?v=4","gravatar_id":"","url":"https://api.github.com/users/wolever","html_url":"https://github.com/wolever","followers_url":"https://api.github.com/users/wolever/followers","following_url":"https://api.github.com/users/wolever/following{/other_user}","gists_url":"https://api.github.com/users/wolever/gists{/gist_id}","starred_url":"https://api.github.com/users/wolever/starred{/owner}{/repo}","subscriptions_url":"https://api.github.com/users/wolever/subscriptions","organizations_url":"https://api.github.com/users/wolever/orgs","repos_url":"https://api.github.com/users/wolever/repos","events_url":"https://api.github.com/users/wolever/events{/privacy}","received_events_url":"https://api.github.com/users/wolever/received_events","type":"User","site_admin":false,"name":"David Wolever","company":"Sheertex","blog":"","location":"Montreal, QC","email":"david@wolever.net","hireable":null,"bio":null,"twitter_username":"wolever","public_repos":104,"public_gists":137,"followers":320,"following":9,"created_at":"2009-03-03T03:28:14Z","updated_at":"2021-05-17T20:24:37Z"}