{"login":"cshaffer","id":2308312,"node_id":"MDQ6VXNlcjIzMDgzMTI=","avatar_url":"https://avatars.githubusercontent.com/u/2308312?v=4","gravatar_id":"","url":"https://api.github.com/users/cshaffer","html_url":"https://github.com/cshaffer","followers_url":"https://api.github.com/users/cshaffer/followers","following_url":"https://api.github.com/users/cshaffer/following{/other_user}","gists_url":"https://api.github.com/users/cshaffer/gists{/gist_id}","starred_url":"https://api.github.com/users/cshaffer/starred{/owner}{/repo}","subscriptions_url":"https://api.github.com/users/cshaffer/subscriptions","organizations_url":"https://api.github.com/users/cshaffer/orgs","repos_url":"https://api.github.com/users/cshaffer/repos","events_url":"https://api.github.com/users/cshaffer/events{/privacy}","received_events_url":"https://api.github.com/users/cshaffer/received_events","type":"User","site_admin":false,"name":"Chad Shaffer","company":"@mycase ","blog":"chadshaffer.com","location":"San Diego, California","email":"chad.russell.shaffer@gmail.com","hireable":null,"bio":null,"twitter_username":null,"public_repos":20,"public_gists":0,"followers":5,"following":0,"created_at":"2012-09-08T21:32:37Z","updated_at":"2021-05-11T13:36:40Z"}