{"login":"DandelionSprout","id":22780683,"node_id":"MDQ6VXNlcjIyNzgwNjgz","avatar_url":"https://avatars.githubusercontent.com/u/22780683?v=4","gravatar_id":"","url":"https://api.github.com/users/DandelionSprout","html_url":"https://github.com/DandelionSprout","followers_url":"https://api.github.com/users/DandelionSprout/followers","following_url":"https://api.github.com/users/DandelionSprout/following{/other_user}","gists_url":"https://api.github.com/users/DandelionSprout/gists{/gist_id}","starred_url":"https://api.github.com/users/DandelionSprout/starred{/owner}{/repo}","subscriptions_url":"https://api.github.com/users/DandelionSprout/subscriptions","organizations_url":"https://api.github.com/users/DandelionSprout/orgs","repos_url":"https://api.github.com/users/DandelionSprout/repos","events_url":"https://api.github.com/users/DandelionSprout/events{/privacy}","received_events_url":"https://api.github.com/users/DandelionSprout/received_events","type":"User","site_admin":false,"name":"Imre Kristoffer Eilertsen","company":null,"blog":"https://sproutsluckycorner.wordpress.com/2017/11/14/my-work-and-contact-resume/","location":"Winter Woods (i.e. Norway)","email":"imreeil42@gmail.com","hireable":true,"bio":"A largely cutesy fellow who enjoys experimenting with new tech, and who enjoys translating programs to Norwegian and making many lists for many web extensions.","twitter_username":null,"public_repos":129,"public_gists":0,"followers":68,"following":0,"created_at":"2016-10-11T23:03:25Z","updated_at":"2021-05-05T16:08:36Z"}