{"login":"fchapoton","id":5454848,"node_id":"MDQ6VXNlcjU0NTQ4NDg=","avatar_url":"https://avatars.githubusercontent.com/u/5454848?v=4","gravatar_id":"","url":"https://api.github.com/users/fchapoton","html_url":"https://github.com/fchapoton","followers_url":"https://api.github.com/users/fchapoton/followers","following_url":"https://api.github.com/users/fchapoton/following{/other_user}","gists_url":"https://api.github.com/users/fchapoton/gists{/gist_id}","starred_url":"https://api.github.com/users/fchapoton/starred{/owner}{/repo}","subscriptions_url":"https://api.github.com/users/fchapoton/subscriptions","organizations_url":"https://api.github.com/users/fchapoton/orgs","repos_url":"https://api.github.com/users/fchapoton/repos","events_url":"https://api.github.com/users/fchapoton/events{/privacy}","received_events_url":"https://api.github.com/users/fchapoton/received_events","type":"User","site_admin":false,"name":"Frédéric Chapoton","company":null,"blog":"https://irma.math.unistra.fr/~chapoton/","location":null,"email":null,"hireable":null,"bio":null,"twitter_username":null,"public_repos":131,"public_gists":0,"followers":5,"following":0,"created_at":"2013-09-13T20:25:26Z","updated_at":"2021-05-19T07:09:03Z"}