{"login":"Lekensteyn","id":164530,"node_id":"MDQ6VXNlcjE2NDUzMA==","avatar_url":"https://avatars.githubusercontent.com/u/164530?v=4","gravatar_id":"","url":"https://api.github.com/users/Lekensteyn","html_url":"https://github.com/Lekensteyn","followers_url":"https://api.github.com/users/Lekensteyn/followers","following_url":"https://api.github.com/users/Lekensteyn/following{/other_user}","gists_url":"https://api.github.com/users/Lekensteyn/gists{/gist_id}","starred_url":"https://api.github.com/users/Lekensteyn/starred{/owner}{/repo}","subscriptions_url":"https://api.github.com/users/Lekensteyn/subscriptions","organizations_url":"https://api.github.com/users/Lekensteyn/orgs","repos_url":"https://api.github.com/users/Lekensteyn/repos","events_url":"https://api.github.com/users/Lekensteyn/events{/privacy}","received_events_url":"https://api.github.com/users/Lekensteyn/received_events","type":"User","site_admin":false,"name":"Peter Wu","company":null,"blog":"https://lekensteyn.nl/","location":"The Netherlands","email":"peter@lekensteyn.nl","hireable":null,"bio":null,"twitter_username":"Lekensteyn","public_repos":172,"public_gists":23,"followers":231,"following":4,"created_at":"2009-12-08T17:30:01Z","updated_at":"2021-05-03T14:26:59Z"}