{"login":"pkukielka","id":1519649,"node_id":"MDQ6VXNlcjE1MTk2NDk=","avatar_url":"https://avatars.githubusercontent.com/u/1519649?v=4","gravatar_id":"","url":"https://api.github.com/users/pkukielka","html_url":"https://github.com/pkukielka","followers_url":"https://api.github.com/users/pkukielka/followers","following_url":"https://api.github.com/users/pkukielka/following{/other_user}","gists_url":"https://api.github.com/users/pkukielka/gists{/gist_id}","starred_url":"https://api.github.com/users/pkukielka/starred{/owner}{/repo}","subscriptions_url":"https://api.github.com/users/pkukielka/subscriptions","organizations_url":"https://api.github.com/users/pkukielka/orgs","repos_url":"https://api.github.com/users/pkukielka/repos","events_url":"https://api.github.com/users/pkukielka/events{/privacy}","received_events_url":"https://api.github.com/users/pkukielka/received_events","type":"User","site_admin":false,"name":"Piotr Kukie³ka","company":"VirtusLab","blog":"http://pkukielka.github.io","location":"Poland","email":null,"hireable":true,"bio":null,"twitter_username":null,"public_repos":39,"public_gists":13,"followers":21,"following":10,"created_at":"2012-03-09T10:38:56Z","updated_at":"2021-05-14T08:23:25Z"}