{"login":"veger","id":171827,"node_id":"MDQ6VXNlcjE3MTgyNw==","avatar_url":"https://avatars.githubusercontent.com/u/171827?v=4","gravatar_id":"","url":"https://api.github.com/users/veger","html_url":"https://github.com/veger","followers_url":"https://api.github.com/users/veger/followers","following_url":"https://api.github.com/users/veger/following{/other_user}","gists_url":"https://api.github.com/users/veger/gists{/gist_id}","starred_url":"https://api.github.com/users/veger/starred{/owner}{/repo}","subscriptions_url":"https://api.github.com/users/veger/subscriptions","organizations_url":"https://api.github.com/users/veger/orgs","repos_url":"https://api.github.com/users/veger/repos","events_url":"https://api.github.com/users/veger/events{/privacy}","received_events_url":"https://api.github.com/users/veger/received_events","type":"User","site_admin":false,"name":"Maarten Bezemer","company":"@jexia-com","blog":"","location":null,"email":null,"hireable":null,"bio":null,"twitter_username":null,"public_repos":50,"public_gists":0,"followers":29,"following":0,"created_at":"2009-12-24T17:17:57Z","updated_at":"2021-05-17T13:25:49Z"}