{"login":"vivamexico","id":7562231,"node_id":"MDQ6VXNlcjc1NjIyMzE=","avatar_url":"https://avatars.githubusercontent.com/u/7562231?v=4","gravatar_id":"","url":"https://api.github.com/users/vivamexico","html_url":"https://github.com/vivamexico","followers_url":"https://api.github.com/users/vivamexico/followers","following_url":"https://api.github.com/users/vivamexico/following{/other_user}","gists_url":"https://api.github.com/users/vivamexico/gists{/gist_id}","starred_url":"https://api.github.com/users/vivamexico/starred{/owner}{/repo}","subscriptions_url":"https://api.github.com/users/vivamexico/subscriptions","organizations_url":"https://api.github.com/users/vivamexico/orgs","repos_url":"https://api.github.com/users/vivamexico/repos","events_url":"https://api.github.com/users/vivamexico/events{/privacy}","received_events_url":"https://api.github.com/users/vivamexico/received_events","type":"User","site_admin":false,"name":null,"company":null,"blog":"","location":null,"email":null,"hireable":null,"bio":null,"twitter_username":null,"public_repos":3,"public_gists":0,"followers":0,"following":0,"created_at":"2014-05-12T20:20:34Z","updated_at":"2021-02-04T21:56:19Z"}